pymacgen/__init__.py
pymacgen/__main__.py
pymacgen-1.0.0.dist-info/METADATA
pymacgen-1.0.0.dist-info/WHEEL
pymacgen-1.0.0.dist-info/entry_points.txt
pymacgen-1.0.0.dist-info/licenses/LICENSE
pymacgen-1.0.0.dist-info/RECORD
