Metadata-Version: 2.4
Name: pymacgen
Version: 1.0.0
Summary: generate mac addresses
Project-URL: Homepage, https://github.com/nbdy/pymacgen
Project-URL: Repository, https://github.com/nbdy/pymacgen
Author-email: Pascal Eberlein <pascal@eberlein.io>
License: MIT License
License-File: LICENSE
Keywords: generator,mac,oui
Classifier: Development Status :: 3 - Alpha
Classifier: Intended Audience :: Developers
Classifier: License :: OSI Approved :: MIT License
Classifier: Programming Language :: Python :: 3
Classifier: Programming Language :: Python :: 3 :: Only
Classifier: Programming Language :: Python :: 3.7
Classifier: Topic :: Software Development :: Build Tools
Requires-Python: >=3.9
Requires-Dist: loguru==0.7.3
Requires-Dist: pyoui==1.0.1
